[{"id": "824523969715170", "seller_name": "\u6676\u6676\u4e66\u5c4b_2008", "create_time": "2014-10-22 13:40:54", "status_info": "\u4ea4\u6613\u5173\u95ed", "sub_orders": [{"product_name": "\u6df1\u5165\u7406\u89e3LINUX\u5185\u6838+LINUX\u8bbe\u5907\u9a71\u52a8\u7a0b\u5e8f(\u7b2c3\u7248) \u535a\u97e6 \u51712\u672c \u9001\u89c6\u9891", "price": "32.00"}]}, {"id": "823645100785170", "seller_name": "\u6676\u6676\u4e66\u5c4b_2008", "create_time": "2014-10-22 13:29:29", "status_info": "\u4ea4\u6613\u5173\u95ed", "sub_orders": [{"product_name": "\u6df1\u5165\u7406\u89e3LINUX\u5185\u6838+LINUX\u8bbe\u5907\u9a71\u52a8\u7a0b\u5e8f(\u7b2c3\u7248) \u535a\u97e6 \u51712\u672c \u9001\u89c6\u9891", "price": "32.00"}]}, {"id": "822460525295170", "seller_name": "iloveyou0564", "create_time": "2014-10-20 07:47:10", "status_info": "\u4ea4\u6613\u6210\u529f", "sub_orders": [{"product_name": "\u53cc\u5347\u964d360\u5ea6\u65cb\u8f6c\u591a\u529f\u80fd\u98ce\u6247\u6563\u70ed\u61d2\u4eba\u7b14\u8bb0\u672c\u7535\u8111\u684c\u7f6e\u5730\u79fb\u52a8\u5e8a\u8fb9\u684c", "price": "158.40"}]}, {"id": "819998797045170", "seller_name": "\u5929\u51e1\u7535\u5668\u4e13\u8425\u5e97", "create_time": "2014-10-18 17:25:14", "status_info": "\u4ea4\u6613\u6210\u529f", "sub_orders": [{"product_name": "\u5e7f\u5dde\u6a31\u82b1\u7535\u5668\u5b9e\u4e1a\u6709\u9650\u516c\u53f8 \u5b98\u65b9\u6b63\u54c1 \u71c3\u6c14\u7076 \u7164\u6c14\u7076\u5177\u7089\u5177", "price": "48.00"}, {"product_name": "\u589e\u503c\u670d\u52a1\uff1a\u9001\u8d27\u5165\u6237", "price": "0.00"}, {"product_name": "\u589e\u503c\u670d\u52a1\uff1a\u5168\u56fd\u8054\u4fdd", "price": "0.00"}, {"product_name": "\u4fdd\u9669\u670d\u52a1", "price": "0.00"}]}, {"id": "820156133655170", "seller_name": "\u80e1\u5251\u4eac", "create_time": "2014-10-17 14:57:00", "status_info": "\u4ea4\u6613\u6210\u529f", "sub_orders": [{"product_name": "Joyoung/\u4e5d\u9633 DJ13B-D81SG    \u5047\u4e00\u8d54\u5341 \u4e5d\u9633 DJ13B-D81SG\u6b63\u54c1", "price": "596.00"}, {"product_name": "\u4fdd\u9669\u670d\u52a1", "price": "26.82"}]}, {"id": "816331993945170", "seller_name": "puzhangyi123", "create_time": "2014-10-14 13:22:28", "status_info": "\u4ea4\u6613\u6210\u529f", "sub_orders": [{"product_name": "\u9999\u6e2f\u514d\u5907\u6848php\u7a7a\u95f4 \u6708\u4ed81G linux\u865a\u62df\u4e3b\u673a \u9ad8\u901f\u7a33\u5b9a \u7ea2\u8272\u6d6a\u70b9\u4e3b\u673a", "price": "8.00"}]}, {"id": "815363581585170", "seller_name": "\u82cf\u6851\u7535\u5668\u4e13\u8425\u5e97", "create_time": "2014-10-12 19:56:06", "status_info": "\u4ea4\u6613\u6210\u529f", "sub_orders": [{"product_name": "\u79cb\u53f6\u539f Q-2103 \u6709\u7ebf\u7535\u89c6\u7ebf 75-5\u540c\u8f74\u7535\u7f06 \u9ad8\u6e05\u95ed\u8def\u7ebf RF\u5c04\u9891\u7ebf 4P", "price": "1.87"}, {"product_name": "\u79cb\u53f6\u539f Q-563A \u97f3\u9891\u7ebf 3.5mm\u516c\u5bf9\u516c aux\u8f66\u8f7d\u624b\u673aMP3 \u8033\u673a\u8fde\u63a5\u7ebf", "price": "8.93"}]}, {"id": "815333827655170", "seller_name": "\u4e9a\u65af\u7279\u81ea\u884c\u8f66\u914d\u4ef6\u6279\u53d1\u5546\u57ce", "create_time": "2014-10-12 19:19:51", "status_info": "\u4ea4\u6613\u5173\u95ed", "sub_orders": [{"product_name": "\u81ea\u884c\u8f66/\u6298\u53e0\u8f66 \u94dd\u5408\u91d1T\u578b\u8f66\u628a14\u5bf820\u5bf8\u6298\u53e0\u8f66\u4e13\u7528\u9f99\u5934\u8f66\u628a\u76f4\u628a", "price": "9.98"}, {"product_name": "\u4fdd\u9669\u670d\u52a1", "price": "0.60"}]}, {"id": "815333267445170", "seller_name": "\u4e9a\u65af\u7279\u81ea\u884c\u8f66\u914d\u4ef6\u6279\u53d1\u5546\u57ce", "create_time": "2014-10-12 19:19:09", "status_info": "\u4ea4\u6613\u6210\u529f", "sub_orders": [{"product_name": "\u81ea\u884c\u8f66/\u6298\u53e0\u8f66 \u94dd\u5408\u91d1T\u578b\u8f66\u628a14\u5bf820\u5bf8\u6298\u53e0\u8f66\u4e13\u7528\u9f99\u5934\u8f66\u628a\u76f4\u628a", "price": "9.98"}, {"product_name": "\u4fdd\u9669\u670d\u52a1", "price": "0.60"}]}, {"id": "813436538445170", "seller_name": "\u6dd8\u6211\u6240\u7231yin", "create_time": "2014-10-09 17:40:23", "status_info": "\u4ea4\u6613\u6210\u529f", "sub_orders": [{"product_name": "\u70ed\u5356\uff01\u4e50\u5149n960\u8d85\u7ea7\u5927\u529f\u7387\u65e0\u7ebf\u7f51\u5361WIFI/CMCC/WLAN\u7a7f\u5899\u589e\u5f3a\u63a5\u6536\u5668", "price": "162.31"}, {"product_name": "\u4fdd\u9669\u670d\u52a1", "price": "0.90"}]}, {"id": "806863651685170", "seller_name": "pintop\u54c1\u6258\u65d7\u8230\u5e97", "create_time": "2014-10-01 10:16:52", "status_info": "\u4ea4\u6613\u5173\u95ed", "sub_orders": [{"product_name": "\u54c1\u6258USB\u5927\u529f\u7387\u65e0\u7ebf\u7f51\u53618187L\u82af\u7247WLAN\u5361\u738b\u5361\u7687WIFI\u4fe1\u53f7\u589e\u5f3a\u63a5\u6536\u5668", "price": "75.00"}, {"product_name": "\u4fdd\u9669\u670d\u52a1", "price": "0.00"}]}, {"id": "797316379415170", "seller_name": "zzyy1681681", "create_time": "2014-09-18 17:40:13", "status_info": "\u4ea4\u6613\u6210\u529f", "sub_orders": [{"product_name": "\u7537\u58eb\u589e\u9ad8\u978b\u5546\u52a1\u6b63\u88c5\u76ae\u978b\u7cfb\u5e26\u82f1\u4f26\u7537\u9690\u5f62\u5185\u589e\u9ad8\u76ae\u978b\u771f\u76ae\u65b0\u90ce\u7ed3\u5a5a\u978b", "price": "79.00"}]}, {"id": "795411084665170", "seller_name": "onlylinxiuwei", "create_time": "2014-09-16 10:23:53", "status_info": "\u4ea4\u6613\u6210\u529f", "sub_orders": [{"product_name": "30\u4e2a\u7248\u672c\u5927\u5168\u53ef\u9009Debian Linux 7/6/5/4 DVD\u7cfb\u7edf\u5b89\u88c5\u5149\u76d832/64\u4f4d", "price": "5.00"}, {"product_name": "30\u4e2a\u7248\u672c\u5927\u5168\u53ef\u9009Debian Linux 7/6/5/4 DVD\u7cfb\u7edf\u5b89\u88c5\u5149\u76d832/64\u4f4d", "price": "5.00"}]}, {"id": "794565107235170", "seller_name": "\u5353\u5efa\u8ba4", "create_time": "2014-09-16 07:57:55", "status_info": "\u4ea4\u6613\u5173\u95ed", "sub_orders": [{"product_name": "\u5305\u90ae\u9999\u8549\u5149\u76d8CD-RW\u53ef\u64e6\u5199\u5149\u76d8\u7a7a\u767d\u523b\u5f55\u76d8 700M\u53ef\u91cd\u590d\u523b\u5f55\u76d810\u7247\u88c5", "price": "19.99"}]}, {"id": "794189991395170", "seller_name": "\u5353\u5efa\u8ba4", "create_time": "2014-09-16 07:10:53", "status_info": "\u4ea4\u6613\u6210\u529f", "sub_orders": [{"product_name": "\u5305\u90ae\u9999\u8549\u5149\u76d8CD-RW\u53ef\u64e6\u5199\u5149\u76d8\u7a7a\u767d\u523b\u5f55\u76d8 700M\u53ef\u91cd\u590d\u523b\u5f55\u76d810\u7247\u88c5", "price": "19.99"}]}]